cubencrypt/Cube.py
cubencrypt/__init__.py
cubencrypt-1.2.dist-info/LICENSE
cubencrypt-1.2.dist-info/METADATA
cubencrypt-1.2.dist-info/WHEEL
cubencrypt-1.2.dist-info/top_level.txt
cubencrypt-1.2.dist-info/RECORD
