Metadata-Version: 2.1
Name: cubencrypt
Version: 1.2
Summary: Package to encrypt and decrypt strings
Home-page: https://github.com/bartoszprokopowicz/CubeEncrypt
Author: Bartosz Prokopowicz
Author-email: bartosz.prokopowicz.97@gmail.com
License: MIT
Platform: UNKNOWN
Classifier: Programming Language :: Python :: 3
Classifier: License :: OSI Approved :: MIT License
Classifier: Operating System :: OS Independent
